{
  "id": "7937564",
  "name": "でかリボンカチューシャ",
  "variations": {
    "default": [
      {
        "date": "2026-02-03",
        "price": 100,
        "is_sale": false
      },
      {
        "date": "2026-02-05",
        "price": 100,
        "is_sale": false
      },
      {
        "date": "2026-02-06",
        "price": 200,
        "is_sale": false
      },
      {
        "date": "2026-02-08",
        "price": 200,
        "is_sale": false
      },
      {
        "date": "2026-02-09",
        "price": 200,
        "is_sale": false
      },
      {
        "date": "2026-02-10",
        "price": 200,
        "is_sale": false
      }
    ]
  }
}