{
  "id": "8031307",
  "name": "コンデンサ型イヤリング",
  "variations": {
    "default": [
      {
        "date": "2026-02-27",
        "price": 340,
        "is_sale": false
      },
      {
        "date": "2026-02-28",
        "price": 340,
        "is_sale": false
      },
      {
        "date": "2026-03-01",
        "price": 340,
        "is_sale": false
      },
      {
        "date": "2026-03-02",
        "price": 340,
        "is_sale": false
      },
      {
        "date": "2026-03-04",
        "price": 340,
        "is_sale": false
      },
      {
        "date": "2026-03-06",
        "price": 340,
        "is_sale": false
      },
      {
        "date": "2026-03-07",
        "price": 340,
        "is_sale": false
      },
      {
        "date": "2026-03-08",
        "price": 340,
        "is_sale": false
      },
      {
        "date": "2026-03-09",
        "price": 340,
        "is_sale": false
      },
      {
        "date": "2026-03-10",
        "price": 340,
        "is_sale": false
      },
      {
        "date": "2026-03-11",
        "price": 340,
        "is_sale": false
      }
    ]
  }
}