{
  "id": "5231318",
  "name": "[FBX] コックスコーム（ジェスター・ハット）Bi-Color🪙",
  "variations": {
    "default": [
      {
        "date": "2026-01-18",
        "price": 510,
        "is_sale": false
      },
      {
        "date": "2026-01-19",
        "price": 510,
        "is_sale": false
      },
      {
        "date": "2026-01-20",
        "price": 510,
        "is_sale": false
      },
      {
        "date": "2026-01-22",
        "price": 510,
        "is_sale": false
      },
      {
        "date": "2026-01-23",
        "price": 510,
        "is_sale": false
      },
      {
        "date": "2026-01-25",
        "price": 510,
        "is_sale": false
      },
      {
        "date": "2026-01-26",
        "price": 510,
        "is_sale": false
      },
      {
        "date": "2026-01-27",
        "price": 510,
        "is_sale": false
      },
      {
        "date": "2026-01-28",
        "price": 510,
        "is_sale": false
      },
      {
        "date": "2026-01-29",
        "price": 510,
        "is_sale": false
      },
      {
        "date": "2026-01-30",
        "price": 510,
        "is_sale": false
      },
      {
        "date": "2026-01-31",
        "price": 510,
        "is_sale": false
      },
      {
        "date": "2026-02-02",
        "price": 510,
        "is_sale": false
      }
    ]
  }
}