{
  "id": "7373771",
  "name": "Touch Feedback System for イチゴIchigo 撫でると表情が変わる！",
  "variations": {
    "TFS for Ichigo": [
      {
        "date": "2026-01-16",
        "price": 500,
        "is_sale": false
      },
      {
        "date": "2026-01-18",
        "price": 500,
        "is_sale": false
      },
      {
        "date": "2026-01-20",
        "price": 500,
        "is_sale": false
      },
      {
        "date": "2026-01-21",
        "price": 500,
        "is_sale": false
      },
      {
        "date": "2026-01-23",
        "price": 500,
        "is_sale": false
      },
      {
        "date": "2026-01-24",
        "price": 500,
        "is_sale": false
      },
      {
        "date": "2026-01-25",
        "price": 500,
        "is_sale": false
      }
    ],
    "エスプレッソ一杯(同じ内容)": [
      {
        "date": "2026-01-16",
        "price": 600,
        "is_sale": false
      },
      {
        "date": "2026-01-18",
        "price": 600,
        "is_sale": false
      },
      {
        "date": "2026-01-20",
        "price": 600,
        "is_sale": false
      },
      {
        "date": "2026-01-21",
        "price": 600,
        "is_sale": false
      },
      {
        "date": "2026-01-23",
        "price": 600,
        "is_sale": false
      },
      {
        "date": "2026-01-24",
        "price": 600,
        "is_sale": false
      },
      {
        "date": "2026-01-25",
        "price": 600,
        "is_sale": false
      }
    ]
  }
}