{
  "id": "7300546",
  "name": "ガンギマリFace for Milltina",
  "variations": {
    "ガンギマリミルティナ": [
      {
        "date": "2026-01-16",
        "price": 250,
        "is_sale": false
      },
      {
        "date": "2026-01-18",
        "price": 250,
        "is_sale": false
      }
    ],
    "ガンギマリミルティナ（オマケあり）": [
      {
        "date": "2026-01-16",
        "price": 400,
        "is_sale": false
      },
      {
        "date": "2026-01-18",
        "price": 400,
        "is_sale": false
      }
    ]
  }
}