{
  "id": "5707680",
  "name": "【VRChat想定】Bracelet_PowerStone",
  "variations": {
    "default": [
      {
        "date": "2026-01-18",
        "price": 500,
        "is_sale": false
      },
      {
        "date": "2026-01-19",
        "price": 500,
        "is_sale": false
      },
      {
        "date": "2026-01-20",
        "price": 500,
        "is_sale": false
      },
      {
        "date": "2026-01-22",
        "price": 500,
        "is_sale": false
      },
      {
        "date": "2026-01-23",
        "price": 500,
        "is_sale": false
      },
      {
        "date": "2026-01-24",
        "price": 500,
        "is_sale": false
      }
    ]
  }
}