{
  "id": "2227938",
  "name": "【ミーシェちゃん用】ストリートアシメセット【ColofulMagic】",
  "variations": {
    "ストリートアシメセット": [
      {
        "date": "2026-01-18",
        "price": 1500,
        "is_sale": false
      },
      {
        "date": "2026-01-20",
        "price": 1500,
        "is_sale": false
      },
      {
        "date": "2026-01-21",
        "price": 1500,
        "is_sale": false
      },
      {
        "date": "2026-01-22",
        "price": 1500,
        "is_sale": false
      },
      {
        "date": "2026-01-24",
        "price": 1500,
        "is_sale": false
      }
    ],
    "もっちりスリーブパーカー": [
      {
        "date": "2026-01-18",
        "price": 600,
        "is_sale": false
      },
      {
        "date": "2026-01-20",
        "price": 600,
        "is_sale": false
      },
      {
        "date": "2026-01-21",
        "price": 600,
        "is_sale": false
      },
      {
        "date": "2026-01-22",
        "price": 600,
        "is_sale": false
      },
      {
        "date": "2026-01-24",
        "price": 600,
        "is_sale": false
      }
    ],
    "へそ出しオフショルトップス": [
      {
        "date": "2026-01-18",
        "price": 600,
        "is_sale": false
      },
      {
        "date": "2026-01-20",
        "price": 600,
        "is_sale": false
      },
      {
        "date": "2026-01-21",
        "price": 600,
        "is_sale": false
      },
      {
        "date": "2026-01-22",
        "price": 600,
        "is_sale": false
      },
      {
        "date": "2026-01-24",
        "price": 600,
        "is_sale": false
      }
    ],
    "アシンメトリープリーツスカート ＆ 靴": [
      {
        "date": "2026-01-18",
        "price": 600,
        "is_sale": false
      },
      {
        "date": "2026-01-20",
        "price": 600,
        "is_sale": false
      },
      {
        "date": "2026-01-21",
        "price": 600,
        "is_sale": false
      },
      {
        "date": "2026-01-22",
        "price": 600,
        "is_sale": false
      },
      {
        "date": "2026-01-24",
        "price": 600,
        "is_sale": false
      }
    ]
  }
}