{
  "id": "6567710",
  "name": "【無料 / 非推奨（説明欄へ）】VRChatワールド用スタッフルームギミック / Staff Room Gimmick",
  "variations": {
    "本体(v1.0.4)": [
      {
        "date": "2026-01-17",
        "price": 0,
        "is_sale": false
      },
      {
        "date": "2026-01-19",
        "price": 0,
        "is_sale": false
      }
    ],
    "ん！！？！(中身は無料のと同じです！！)": [
      {
        "date": "2026-01-17",
        "price": 200,
        "is_sale": false
      },
      {
        "date": "2026-01-19",
        "price": 200,
        "is_sale": false
      }
    ]
  }
}