{
  "id": "5896151",
  "name": "【VRChat想定・MA対応】星がはじけるパーティクル -twinkle star particles-",
  "variations": {
    "default": [
      {
        "date": "2026-01-18",
        "price": 200,
        "is_sale": false
      },
      {
        "date": "2026-01-19",
        "price": 200,
        "is_sale": false
      },
      {
        "date": "2026-01-20",
        "price": 200,
        "is_sale": false
      },
      {
        "date": "2026-01-22",
        "price": 200,
        "is_sale": false
      },
      {
        "date": "2026-01-23",
        "price": 200,
        "is_sale": false
      },
      {
        "date": "2026-01-24",
        "price": 200,
        "is_sale": false
      }
    ]
  }
}