{
  "id": "7126877",
  "name": "【無料】笹着ぐるみ【まめふれんず対応】",
  "variations": {
    "笹着ぐるみ": [
      {
        "date": "2026-01-17",
        "price": 0,
        "is_sale": false
      },
      {
        "date": "2026-01-18",
        "price": 0,
        "is_sale": false
      },
      {
        "date": "2026-01-20",
        "price": 0,
        "is_sale": false
      },
      {
        "date": "2026-01-21",
        "price": 0,
        "is_sale": false
      },
      {
        "date": "2026-01-23",
        "price": 0,
        "is_sale": false
      },
      {
        "date": "2026-01-24",
        "price": 0,
        "is_sale": false
      }
    ],
    "支援版(Tシャツ付)": [
      {
        "date": "2026-01-17",
        "price": 100,
        "is_sale": false
      },
      {
        "date": "2026-01-18",
        "price": 100,
        "is_sale": false
      },
      {
        "date": "2026-01-20",
        "price": 100,
        "is_sale": false
      },
      {
        "date": "2026-01-21",
        "price": 100,
        "is_sale": false
      },
      {
        "date": "2026-01-23",
        "price": 100,
        "is_sale": false
      },
      {
        "date": "2026-01-24",
        "price": 100,
        "is_sale": false
      }
    ]
  }
}