{
  "id": "3699753",
  "name": "3DCG【studio_set】レコーディングスタジオルーム ミキサー　コンソール",
  "variations": {
    "studioセット": [
      {
        "date": "2026-01-18",
        "price": 1500,
        "is_sale": false
      },
      {
        "date": "2026-01-20",
        "price": 1500,
        "is_sale": false
      },
      {
        "date": "2026-01-21",
        "price": 1500,
        "is_sale": false
      }
    ],
    "ミキサー(コンソール)のみ": [
      {
        "date": "2026-01-18",
        "price": 1000,
        "is_sale": false
      },
      {
        "date": "2026-01-20",
        "price": 1000,
        "is_sale": false
      },
      {
        "date": "2026-01-21",
        "price": 1000,
        "is_sale": false
      }
    ],
    "studioセット(clip studio MODELERデータ)": [
      {
        "date": "2026-01-18",
        "price": 500,
        "is_sale": false
      },
      {
        "date": "2026-01-20",
        "price": 500,
        "is_sale": false
      },
      {
        "date": "2026-01-21",
        "price": 500,
        "is_sale": false
      }
    ]
  }
}