{
  "id": "6169221",
  "name": "【アイテクスチャ】マヌカ専用 きらめく銀河",
  "variations": {
    "default": [
      {
        "date": "2026-01-17",
        "price": 300,
        "is_sale": false
      },
      {
        "date": "2026-01-19",
        "price": 300,
        "is_sale": false
      },
      {
        "date": "2026-01-20",
        "price": 300,
        "is_sale": false
      },
      {
        "date": "2026-01-22",
        "price": 300,
        "is_sale": false
      },
      {
        "date": "2026-01-23",
        "price": 300,
        "is_sale": false
      },
      {
        "date": "2026-01-24",
        "price": 300,
        "is_sale": false
      },
      {
        "date": "2026-01-25",
        "price": 300,
        "is_sale": false
      },
      {
        "date": "2026-01-26",
        "price": 300,
        "is_sale": false
      },
      {
        "date": "2026-01-27",
        "price": 300,
        "is_sale": false
      },
      {
        "date": "2026-01-28",
        "price": 300,
        "is_sale": false
      },
      {
        "date": "2026-01-29",
        "price": 300,
        "is_sale": false
      }
    ]
  }
}