{
  "id": "8052564",
  "name": "みみのこショートカット",
  "variations": {
    "作りっぱなし版": [
      {
        "date": "2026-03-06",
        "price": 0,
        "is_sale": false
      },
      {
        "date": "2026-03-07",
        "price": 0,
        "is_sale": false
      },
      {
        "date": "2026-03-08",
        "price": 0,
        "is_sale": false
      },
      {
        "date": "2026-03-09",
        "price": 0,
        "is_sale": false
      },
      {
        "date": "2026-03-10",
        "price": 0,
        "is_sale": false
      },
      {
        "date": "2026-03-11",
        "price": 0,
        "is_sale": false
      },
      {
        "date": "2026-03-13",
        "price": 0,
        "is_sale": false
      },
      {
        "date": "2026-03-14",
        "price": 0,
        "is_sale": false
      }
    ],
    "アプデする版": [
      {
        "date": "2026-03-06",
        "price": 300,
        "is_sale": false
      },
      {
        "date": "2026-03-07",
        "price": 300,
        "is_sale": false
      },
      {
        "date": "2026-03-08",
        "price": 300,
        "is_sale": false
      },
      {
        "date": "2026-03-09",
        "price": 300,
        "is_sale": false
      },
      {
        "date": "2026-03-10",
        "price": 300,
        "is_sale": false
      },
      {
        "date": "2026-03-11",
        "price": 300,
        "is_sale": false
      },
      {
        "date": "2026-03-13",
        "price": 300,
        "is_sale": false
      },
      {
        "date": "2026-03-14",
        "price": 300,
        "is_sale": false
      }
    ]
  }
}