{
  "id": "1576656",
  "name": "【HELLKAWAII】ヘルカワα/β【VRChat向け3Dモデル】",
  "variations": {
    "【2体セット】ヘルカワα&β【お得な】": [
      {
        "date": "2026-01-18",
        "price": 5000,
        "is_sale": false
      },
      {
        "date": "2026-01-20",
        "price": 5000,
        "is_sale": false
      },
      {
        "date": "2026-01-21",
        "price": 5000,
        "is_sale": false
      },
      {
        "date": "2026-01-22",
        "price": 5000,
        "is_sale": false
      }
    ],
    "【赤い方】ヘルカワα【ジャケット装備】": [
      {
        "date": "2026-01-18",
        "price": 3000,
        "is_sale": false
      },
      {
        "date": "2026-01-20",
        "price": 3000,
        "is_sale": false
      },
      {
        "date": "2026-01-21",
        "price": 3000,
        "is_sale": false
      },
      {
        "date": "2026-01-22",
        "price": 3000,
        "is_sale": false
      }
    ],
    "【青い方】ヘルカワβ【スカート装備】": [
      {
        "date": "2026-01-18",
        "price": 3000,
        "is_sale": false
      },
      {
        "date": "2026-01-20",
        "price": 3000,
        "is_sale": false
      },
      {
        "date": "2026-01-21",
        "price": 3000,
        "is_sale": false
      },
      {
        "date": "2026-01-22",
        "price": 3000,
        "is_sale": false
      }
    ]
  }
}