{
  "id": "5356136",
  "name": "【ニール対応】姫袖王子ロリィタ",
  "variations": {
    "利用規約(ja/en/ko/zh)": [
      {
        "date": "2026-01-18",
        "price": 0,
        "is_sale": false
      },
      {
        "date": "2026-01-19",
        "price": 0,
        "is_sale": false
      },
      {
        "date": "2026-01-20",
        "price": 0,
        "is_sale": false
      },
      {
        "date": "2026-01-22",
        "price": 0,
        "is_sale": false
      },
      {
        "date": "2026-01-23",
        "price": 0,
        "is_sale": false
      },
      {
        "date": "2026-01-25",
        "price": 0,
        "is_sale": false
      },
      {
        "date": "2026-01-26",
        "price": 0,
        "is_sale": false
      },
      {
        "date": "2026-01-27",
        "price": 0,
        "is_sale": false
      }
    ],
    "【ニール対応】姫袖王子ロリィタ": [
      {
        "date": "2026-01-18",
        "price": 2500,
        "is_sale": false
      },
      {
        "date": "2026-01-19",
        "price": 2500,
        "is_sale": false
      },
      {
        "date": "2026-01-20",
        "price": 2500,
        "is_sale": false
      },
      {
        "date": "2026-01-22",
        "price": 2500,
        "is_sale": false
      },
      {
        "date": "2026-01-23",
        "price": 2500,
        "is_sale": false
      },
      {
        "date": "2026-01-25",
        "price": 2500,
        "is_sale": false
      },
      {
        "date": "2026-01-26",
        "price": 2500,
        "is_sale": false
      },
      {
        "date": "2026-01-27",
        "price": 2500,
        "is_sale": false
      }
    ]
  }
}