{
  "id": "3004016",
  "name": "キーボードスタンド・スタッカーセット△2310 | VRChat想定",
  "variations": {
    "個人利用ライセンス": [
      {
        "date": "2026-01-18",
        "price": 190,
        "is_sale": false
      },
      {
        "date": "2026-01-20",
        "price": 190,
        "is_sale": false
      },
      {
        "date": "2026-01-21",
        "price": 190,
        "is_sale": false
      },
      {
        "date": "2026-01-22",
        "price": 190,
        "is_sale": false
      },
      {
        "date": "2026-01-23",
        "price": 190,
        "is_sale": false
      },
      {
        "date": "2026-01-25",
        "price": 190,
        "is_sale": false
      },
      {
        "date": "2026-01-26",
        "price": 190,
        "is_sale": false
      },
      {
        "date": "2026-01-27",
        "price": 190,
        "is_sale": false
      }
    ],
    "法人利用/Publicアバター用ライセンス": [
      {
        "date": "2026-01-18",
        "price": 950,
        "is_sale": false
      },
      {
        "date": "2026-01-20",
        "price": 950,
        "is_sale": false
      },
      {
        "date": "2026-01-21",
        "price": 950,
        "is_sale": false
      },
      {
        "date": "2026-01-22",
        "price": 950,
        "is_sale": false
      },
      {
        "date": "2026-01-23",
        "price": 950,
        "is_sale": false
      },
      {
        "date": "2026-01-25",
        "price": 950,
        "is_sale": false
      },
      {
        "date": "2026-01-26",
        "price": 950,
        "is_sale": false
      },
      {
        "date": "2026-01-27",
        "price": 950,
        "is_sale": false
      }
    ]
  }
}