{
  "id": "8202918",
  "name": "【Andrewと舞夜に対応】きゅるきゅるあい",
  "variations": {
    "通常版": [
      {
        "date": "2026-04-17",
        "price": 300,
        "is_sale": false
      },
      {
        "date": "2026-04-18",
        "price": 300,
        "is_sale": false
      },
      {
        "date": "2026-04-20",
        "price": 300,
        "is_sale": false
      },
      {
        "date": "2026-04-21",
        "price": 300,
        "is_sale": false
      },
      {
        "date": "2026-04-23",
        "price": 300,
        "is_sale": false
      },
      {
        "date": "2026-04-24",
        "price": 300,
        "is_sale": false
      },
      {
        "date": "2026-04-26",
        "price": 300,
        "is_sale": false
      },
      {
        "date": "2026-04-27",
        "price": 300,
        "is_sale": false
      },
      {
        "date": "2026-04-28",
        "price": 300,
        "is_sale": false
      }
    ],
    "お好み焼き(内容は同じです)": [
      {
        "date": "2026-04-17",
        "price": 500,
        "is_sale": false
      },
      {
        "date": "2026-04-18",
        "price": 500,
        "is_sale": false
      },
      {
        "date": "2026-04-20",
        "price": 500,
        "is_sale": false
      },
      {
        "date": "2026-04-21",
        "price": 500,
        "is_sale": false
      },
      {
        "date": "2026-04-23",
        "price": 500,
        "is_sale": false
      },
      {
        "date": "2026-04-24",
        "price": 500,
        "is_sale": false
      },
      {
        "date": "2026-04-26",
        "price": 500,
        "is_sale": false
      },
      {
        "date": "2026-04-27",
        "price": 500,
        "is_sale": false
      },
      {
        "date": "2026-04-28",
        "price": 500,
        "is_sale": false
      }
    ]
  }
}