{
  "id": "4039058",
  "name": "【5アバター対応】 Sneakers A",
  "variations": {
    "Sneakers A (All set)": [
      {
        "date": "2026-01-18",
        "price": 390,
        "is_sale": false
      },
      {
        "date": "2026-01-20",
        "price": 390,
        "is_sale": false
      },
      {
        "date": "2026-01-21",
        "price": 390,
        "is_sale": false
      }
    ],
    "【+Donate】 Sneakers A (All set)": [
      {
        "date": "2026-01-18",
        "price": 500,
        "is_sale": false
      },
      {
        "date": "2026-01-20",
        "price": 500,
        "is_sale": false
      },
      {
        "date": "2026-01-21",
        "price": 500,
        "is_sale": false
      }
    ]
  }
}