{
  "id": "6618401",
  "name": "♡Noble Ribbon Beret♡（リボン付きベレー帽）",
  "variations": {
    "通常版": [
      {
        "date": "2026-01-17",
        "price": 500,
        "is_sale": false
      },
      {
        "date": "2026-01-19",
        "price": 500,
        "is_sale": false
      },
      {
        "date": "2026-01-20",
        "price": 500,
        "is_sale": false
      }
    ],
    "お菓子代": [
      {
        "date": "2026-01-17",
        "price": 700,
        "is_sale": false
      },
      {
        "date": "2026-01-19",
        "price": 700,
        "is_sale": false
      },
      {
        "date": "2026-01-20",
        "price": 700,
        "is_sale": false
      }
    ]
  }
}