{
  "id": "5766484",
  "name": "[Lime/Chiffon] Morning ~ Make up Texture + ACC set ~",
  "variations": {
    "++ACC++": [
      {
        "date": "2026-01-18",
        "price": 150,
        "is_sale": false
      },
      {
        "date": "2026-01-19",
        "price": 150,
        "is_sale": false
      }
    ],
    "++Chiffon++": [
      {
        "date": "2026-01-18",
        "price": 450,
        "is_sale": false
      },
      {
        "date": "2026-01-19",
        "price": 450,
        "is_sale": false
      }
    ],
    "++Lime++": [
      {
        "date": "2026-01-18",
        "price": 450,
        "is_sale": false
      },
      {
        "date": "2026-01-19",
        "price": 450,
        "is_sale": false
      }
    ],
    "++Full pack++": [
      {
        "date": "2026-01-18",
        "price": 600,
        "is_sale": false
      },
      {
        "date": "2026-01-19",
        "price": 600,
        "is_sale": false
      }
    ]
  }
}