{
  "id": "5541836",
  "name": "【5アバター対応】花柄きれいワンピース（エルミーナ、萌、マヌカ、ラシューシャ、森羅）",
  "variations": {
    "フルパック（5ファイル）": [
      {
        "date": "2026-01-18",
        "price": 2200,
        "is_sale": false
      },
      {
        "date": "2026-01-19",
        "price": 2200,
        "is_sale": false
      },
      {
        "date": "2026-01-20",
        "price": 2200,
        "is_sale": false
      }
    ],
    "萌-moe-": [
      {
        "date": "2026-01-18",
        "price": 1000,
        "is_sale": false
      },
      {
        "date": "2026-01-19",
        "price": 1000,
        "is_sale": false
      },
      {
        "date": "2026-01-20",
        "price": 1000,
        "is_sale": false
      }
    ],
    "エルミーナ-elmina-": [
      {
        "date": "2026-01-18",
        "price": 1000,
        "is_sale": false
      },
      {
        "date": "2026-01-19",
        "price": 1000,
        "is_sale": false
      },
      {
        "date": "2026-01-20",
        "price": 1000,
        "is_sale": false
      }
    ],
    "マヌカ-manuka-": [
      {
        "date": "2026-01-18",
        "price": 1000,
        "is_sale": false
      },
      {
        "date": "2026-01-19",
        "price": 1000,
        "is_sale": false
      },
      {
        "date": "2026-01-20",
        "price": 1000,
        "is_sale": false
      }
    ],
    "森羅-shinra-": [
      {
        "date": "2026-01-18",
        "price": 1000,
        "is_sale": false
      },
      {
        "date": "2026-01-19",
        "price": 1000,
        "is_sale": false
      },
      {
        "date": "2026-01-20",
        "price": 1000,
        "is_sale": false
      }
    ],
    "ラシューシャ-lasyusya-": [
      {
        "date": "2026-01-18",
        "price": 1000,
        "is_sale": false
      },
      {
        "date": "2026-01-19",
        "price": 1000,
        "is_sale": false
      },
      {
        "date": "2026-01-20",
        "price": 1000,
        "is_sale": false
      }
    ]
  }
}