{
  "id": "4820906",
  "name": "【中華風】倒福イヤリング (dao fu earring)【VRC】",
  "variations": {
    "倒福イヤリング(dao fu　earring)": [
      {
        "date": "2026-01-18",
        "price": 200,
        "is_sale": false
      },
      {
        "date": "2026-01-19",
        "price": 200,
        "is_sale": false
      },
      {
        "date": "2026-01-20",
        "price": 200,
        "is_sale": false
      },
      {
        "date": "2026-01-22",
        "price": 200,
        "is_sale": false
      },
      {
        "date": "2026-01-23",
        "price": 200,
        "is_sale": false
      },
      {
        "date": "2026-01-25",
        "price": 200,
        "is_sale": false
      }
    ],
    "倒福イヤリング+おやつ代(内容は同じです)": [
      {
        "date": "2026-01-18",
        "price": 400,
        "is_sale": false
      },
      {
        "date": "2026-01-19",
        "price": 400,
        "is_sale": false
      },
      {
        "date": "2026-01-20",
        "price": 400,
        "is_sale": false
      },
      {
        "date": "2026-01-22",
        "price": 400,
        "is_sale": false
      },
      {
        "date": "2026-01-23",
        "price": 400,
        "is_sale": false
      },
      {
        "date": "2026-01-25",
        "price": 400,
        "is_sale": false
      }
    ]
  }
}