{
  "id": "4363618",
  "name": "World Pen Shaders Smew Brush QvPen VRChat v2.0",
  "variations": {
    "default": [
      {
        "date": "2026-01-18",
        "price": 700,
        "is_sale": false
      },
      {
        "date": "2026-01-20",
        "price": 700,
        "is_sale": false
      },
      {
        "date": "2026-01-21",
        "price": 700,
        "is_sale": false
      },
      {
        "date": "2026-01-22",
        "price": 700,
        "is_sale": false
      },
      {
        "date": "2026-01-24",
        "price": 700,
        "is_sale": false
      }
    ]
  }
}