{
  "id": "4731727",
  "name": "【VRC向け髪型】スノウショートヘア / Snow Short Hair",
  "variations": {
    "通常版": [
      {
        "date": "2026-01-18",
        "price": 1300,
        "is_sale": false
      },
      {
        "date": "2026-01-19",
        "price": 1300,
        "is_sale": false
      }
    ],
    "コーヒー代を添える（中身は同じです）": [
      {
        "date": "2026-01-18",
        "price": 1400,
        "is_sale": false
      },
      {
        "date": "2026-01-19",
        "price": 1400,
        "is_sale": false
      }
    ],
    "商用利用版（中身は同じです）": [
      {
        "date": "2026-01-18",
        "price": 3000,
        "is_sale": false
      },
      {
        "date": "2026-01-19",
        "price": 3000,
        "is_sale": false
      }
    ]
  }
}