{
  "id": "6750930",
  "name": "パラメーターの感度を調整するやつ（Parameter Sensitivity Editor）",
  "variations": {
    "無料版": [
      {
        "date": "2026-01-18",
        "price": 0,
        "is_sale": false
      },
      {
        "date": "2026-01-20",
        "price": 0,
        "is_sale": false
      },
      {
        "date": "2026-01-21",
        "price": 0,
        "is_sale": false
      },
      {
        "date": "2026-01-22",
        "price": 0,
        "is_sale": false
      }
    ],
    "Donate（無料版と同じです）": [
      {
        "date": "2026-01-18",
        "price": 100,
        "is_sale": false
      },
      {
        "date": "2026-01-20",
        "price": 100,
        "is_sale": false
      },
      {
        "date": "2026-01-21",
        "price": 100,
        "is_sale": false
      },
      {
        "date": "2026-01-22",
        "price": 100,
        "is_sale": false
      }
    ]
  }
}