{
  "id": "4603092",
  "name": "SakuraSet [ #SAKURANO ]",
  "variations": {
    "桜ぼんぼり": [
      {
        "date": "2026-01-18",
        "price": 100,
        "is_sale": false
      }
    ],
    "屏風": [
      {
        "date": "2026-01-18",
        "price": 100,
        "is_sale": false
      }
    ],
    "桜ランタン": [
      {
        "date": "2026-01-18",
        "price": 100,
        "is_sale": false
      }
    ],
    "桜降るパーティクル": [
      {
        "date": "2026-01-18",
        "price": 100,
        "is_sale": false
      }
    ],
    "全てのセット": [
      {
        "date": "2026-01-18",
        "price": 300,
        "is_sale": false
      }
    ]
  }
}