{
  "id": "5659365",
  "name": "[VRC] Sio Skin Enhancements",
  "variations": {
    "Full Package": [
      {
        "date": "2026-01-18",
        "price": 1000,
        "is_sale": false
      },
      {
        "date": "2026-01-19",
        "price": 1000,
        "is_sale": false
      },
      {
        "date": "2026-01-20",
        "price": 1000,
        "is_sale": false
      },
      {
        "date": "2026-01-22",
        "price": 1000,
        "is_sale": false
      },
      {
        "date": "2026-01-23",
        "price": 1000,
        "is_sale": false
      },
      {
        "date": "2026-01-24",
        "price": 1000,
        "is_sale": false
      }
    ],
    "Abs+Pores": [
      {
        "date": "2026-01-18",
        "price": 700,
        "is_sale": false
      },
      {
        "date": "2026-01-19",
        "price": 700,
        "is_sale": false
      },
      {
        "date": "2026-01-20",
        "price": 700,
        "is_sale": false
      },
      {
        "date": "2026-01-22",
        "price": 700,
        "is_sale": false
      },
      {
        "date": "2026-01-23",
        "price": 700,
        "is_sale": false
      },
      {
        "date": "2026-01-24",
        "price": 700,
        "is_sale": false
      }
    ],
    "Wet Only": [
      {
        "date": "2026-01-18",
        "price": 500,
        "is_sale": false
      },
      {
        "date": "2026-01-19",
        "price": 500,
        "is_sale": false
      },
      {
        "date": "2026-01-20",
        "price": 500,
        "is_sale": false
      },
      {
        "date": "2026-01-22",
        "price": 500,
        "is_sale": false
      },
      {
        "date": "2026-01-23",
        "price": 500,
        "is_sale": false
      },
      {
        "date": "2026-01-24",
        "price": 500,
        "is_sale": false
      }
    ],
    "Pores Only": [
      {
        "date": "2026-01-18",
        "price": 200,
        "is_sale": false
      },
      {
        "date": "2026-01-19",
        "price": 200,
        "is_sale": false
      },
      {
        "date": "2026-01-20",
        "price": 200,
        "is_sale": false
      },
      {
        "date": "2026-01-22",
        "price": 200,
        "is_sale": false
      },
      {
        "date": "2026-01-23",
        "price": 200,
        "is_sale": false
      },
      {
        "date": "2026-01-24",
        "price": 200,
        "is_sale": false
      }
    ]
  }
}