{
  "id": "5515254",
  "name": "【無料】セントステラ【オリジナル3Dモデル】",
  "variations": {
    "支援版(中身に違いはありません)": [
      {
        "date": "2026-01-18",
        "price": 100,
        "is_sale": false
      },
      {
        "date": "2026-01-19",
        "price": 100,
        "is_sale": false
      }
    ],
    "無料版": [
      {
        "date": "2026-01-18",
        "price": 0,
        "is_sale": false
      },
      {
        "date": "2026-01-19",
        "price": 0,
        "is_sale": false
      }
    ]
  }
}