{
  "id": "2906861",
  "name": "3 Floors House with 8 Ball 【SDK3 VRChat Ready】 8ボール付き3階建ての家",
  "variations": {
    "default": [
      {
        "date": "2026-01-18",
        "price": 3000,
        "is_sale": false
      },
      {
        "date": "2026-01-20",
        "price": 3000,
        "is_sale": false
      },
      {
        "date": "2026-01-21",
        "price": 3000,
        "is_sale": false
      },
      {
        "date": "2026-01-22",
        "price": 3000,
        "is_sale": false
      },
      {
        "date": "2026-01-23",
        "price": 3000,
        "is_sale": false
      }
    ]
  }
}