{
  "id": "8160371",
  "name": "⏰️【48h 20FREE】⏰️【~4/19SALE】Mayo100Type❥動くまばたきFace&PoseAnimations ⌖ ݁˚",
  "variations": {
    "💝𝐅𝐮𝐥𝐥“𝐌𝐚𝐱𝟏𝟎𝟎”⁺Blink（1,100 → 900SALE）": [
      {
        "date": "2026-04-08",
        "price": 900,
        "is_sale": true
      },
      {
        "date": "2026-04-10",
        "price": 900,
        "is_sale": true
      },
      {
        "date": "2026-04-11",
        "price": 900,
        "is_sale": true
      },
      {
        "date": "2026-04-13",
        "price": 900,
        "is_sale": true
      }
    ],
    "Face50Type♥R18 Including": [
      {
        "date": "2026-04-08",
        "price": 500,
        "is_sale": true
      },
      {
        "date": "2026-04-10",
        "price": 500,
        "is_sale": true
      },
      {
        "date": "2026-04-11",
        "price": 500,
        "is_sale": true
      },
      {
        "date": "2026-04-13",
        "price": 500,
        "is_sale": true
      }
    ],
    "BlinkAnimation♥2Type": [
      {
        "date": "2026-04-08",
        "price": 300,
        "is_sale": true
      },
      {
        "date": "2026-04-10",
        "price": 300,
        "is_sale": true
      },
      {
        "date": "2026-04-11",
        "price": 300,
        "is_sale": true
      },
      {
        "date": "2026-04-13",
        "price": 300,
        "is_sale": true
      }
    ],
    "【FREE❥無料】5FaceAnimation⁺1Pose": [
      {
        "date": "2026-04-08",
        "price": 0,
        "is_sale": true
      },
      {
        "date": "2026-04-10",
        "price": 0,
        "is_sale": true
      },
      {
        "date": "2026-04-11",
        "price": 0,
        "is_sale": true
      },
      {
        "date": "2026-04-13",
        "price": 0,
        "is_sale": true
      }
    ],
    "⏰️48hFREE⏰️": [
      {
        "date": "2026-04-08",
        "price": 0,
        "is_sale": true
      },
      {
        "date": "2026-04-10",
        "price": 0,
        "is_sale": true
      }
    ]
  }
}