{
  "id": "7996553",
  "name": "Shoes oversiZe (6 avatares)",
  "variations": {
    "Full pack": [
      {
        "date": "2026-02-16",
        "price": 1800,
        "is_sale": false
      },
      {
        "date": "2026-02-18",
        "price": 1800,
        "is_sale": false
      }
    ],
    "Lumina": [
      {
        "date": "2026-02-16",
        "price": 1150,
        "is_sale": false
      },
      {
        "date": "2026-02-18",
        "price": 1150,
        "is_sale": false
      }
    ],
    "Manuka": [
      {
        "date": "2026-02-16",
        "price": 1150,
        "is_sale": false
      },
      {
        "date": "2026-02-18",
        "price": 1150,
        "is_sale": false
      }
    ],
    "Shinra": [
      {
        "date": "2026-02-16",
        "price": 1150,
        "is_sale": false
      },
      {
        "date": "2026-02-18",
        "price": 1150,
        "is_sale": false
      }
    ],
    "Shinano": [
      {
        "date": "2026-02-16",
        "price": 1150,
        "is_sale": false
      },
      {
        "date": "2026-02-18",
        "price": 1150,
        "is_sale": false
      }
    ],
    "Miltina": [
      {
        "date": "2026-02-16",
        "price": 1150,
        "is_sale": false
      },
      {
        "date": "2026-02-18",
        "price": 1150,
        "is_sale": false
      }
    ],
    "Kikyo": [
      {
        "date": "2026-02-16",
        "price": 1150,
        "is_sale": false
      },
      {
        "date": "2026-02-18",
        "price": 1150,
        "is_sale": false
      }
    ]
  }
}