{
  "id": "7951959",
  "name": "【泣夜くん専用】EyeTexture　　Cosmic",
  "variations": {
    "default": [
      {
        "date": "2026-02-08",
        "price": 250,
        "is_sale": false
      },
      {
        "date": "2026-02-09",
        "price": 250,
        "is_sale": false
      },
      {
        "date": "2026-02-10",
        "price": 250,
        "is_sale": false
      },
      {
        "date": "2026-02-12",
        "price": 250,
        "is_sale": false
      },
      {
        "date": "2026-02-13",
        "price": 250,
        "is_sale": false
      },
      {
        "date": "2026-02-14",
        "price": 250,
        "is_sale": false
      }
    ]
  }
}