{
  "id": "8010120",
  "name": "【新作SALE】ゆるくまスクール【4アバター対応】",
  "variations": {
    "フルセット/full set": [
      {
        "date": "2026-02-20",
        "price": 1000,
        "is_sale": true
      },
      {
        "date": "2026-02-22",
        "price": 1000,
        "is_sale": true
      }
    ],
    "まめふれんず/mamefriends": [
      {
        "date": "2026-02-20",
        "price": 750,
        "is_sale": true
      },
      {
        "date": "2026-02-22",
        "price": 750,
        "is_sale": true
      }
    ],
    "えも研/emoken": [
      {
        "date": "2026-02-20",
        "price": 750,
        "is_sale": true
      },
      {
        "date": "2026-02-22",
        "price": 750,
        "is_sale": true
      }
    ],
    "エルシオン/elusion": [
      {
        "date": "2026-02-20",
        "price": 750,
        "is_sale": true
      },
      {
        "date": "2026-02-22",
        "price": 750,
        "is_sale": true
      }
    ],
    "ひかるん / hikarun": [
      {
        "date": "2026-02-20",
        "price": 750,
        "is_sale": true
      },
      {
        "date": "2026-02-22",
        "price": 750,
        "is_sale": true
      }
    ]
  }
}