{
  "id": "8176329",
  "name": "【ワールド・環境】荒野 SKYBOXテクスチャ",
  "variations": {
    "default": [
      {
        "date": "2026-04-10",
        "price": 178,
        "is_sale": false
      },
      {
        "date": "2026-04-11",
        "price": 178,
        "is_sale": false
      },
      {
        "date": "2026-04-13",
        "price": 178,
        "is_sale": false
      },
      {
        "date": "2026-04-14",
        "price": 178,
        "is_sale": false
      },
      {
        "date": "2026-04-15",
        "price": 178,
        "is_sale": false
      },
      {
        "date": "2026-04-17",
        "price": 178,
        "is_sale": false
      },
      {
        "date": "2026-04-18",
        "price": 178,
        "is_sale": false
      },
      {
        "date": "2026-04-20",
        "price": 178,
        "is_sale": false
      },
      {
        "date": "2026-04-21",
        "price": 178,
        "is_sale": false
      }
    ]
  }
}