{
  "id": "4962251",
  "name": "アイマスク レザー＆レース",
  "variations": {
    "レザー": [
      {
        "date": "2026-01-18",
        "price": 300,
        "is_sale": false
      },
      {
        "date": "2026-01-19",
        "price": 300,
        "is_sale": false
      }
    ],
    "レース": [
      {
        "date": "2026-01-18",
        "price": 300,
        "is_sale": false
      },
      {
        "date": "2026-01-19",
        "price": 300,
        "is_sale": false
      }
    ],
    "レザー＆レース セット": [
      {
        "date": "2026-01-18",
        "price": 500,
        "is_sale": false
      },
      {
        "date": "2026-01-19",
        "price": 500,
        "is_sale": false
      }
    ]
  }
}