{
  "id": "6404093",
  "name": "TOE_TOE_LY 🦶 | Foot Animation System |",
  "variations": {
    "VR Base": [
      {
        "date": "2026-01-17",
        "price": 2000,
        "is_sale": false
      }
    ],
    "RP Base": [
      {
        "date": "2026-01-17",
        "price": 2000,
        "is_sale": false
      }
    ],
    "Zin Fit Base": [
      {
        "date": "2026-01-17",
        "price": 2000,
        "is_sale": false
      }
    ],
    "Venus Body V2 (2.02)": [
      {
        "date": "2026-01-17",
        "price": 2000,
        "is_sale": false
      }
    ]
  }
}