{
  "id": "5348698",
  "name": "ハウライト・ナースドレス【複数アバター対応】",
  "variations": {
    "フルパック": [
      {
        "date": "2026-01-18",
        "price": 4000,
        "is_sale": false
      },
      {
        "date": "2026-01-19",
        "price": 4000,
        "is_sale": false
      },
      {
        "date": "2026-01-20",
        "price": 4000,
        "is_sale": false
      }
    ],
    "for +Head (カルネ)": [
      {
        "date": "2026-01-18",
        "price": 1500,
        "is_sale": false
      },
      {
        "date": "2026-01-19",
        "price": 1500,
        "is_sale": false
      },
      {
        "date": "2026-01-20",
        "price": 1500,
        "is_sale": false
      }
    ],
    "for マヌカ": [
      {
        "date": "2026-01-18",
        "price": 1500,
        "is_sale": false
      },
      {
        "date": "2026-01-19",
        "price": 1500,
        "is_sale": false
      },
      {
        "date": "2026-01-20",
        "price": 1500,
        "is_sale": false
      }
    ],
    "for 森羅": [
      {
        "date": "2026-01-18",
        "price": 1500,
        "is_sale": false
      },
      {
        "date": "2026-01-19",
        "price": 1500,
        "is_sale": false
      },
      {
        "date": "2026-01-20",
        "price": 1500,
        "is_sale": false
      }
    ],
    "for 水瀬": [
      {
        "date": "2026-01-18",
        "price": 1500,
        "is_sale": false
      },
      {
        "date": "2026-01-19",
        "price": 1500,
        "is_sale": false
      },
      {
        "date": "2026-01-20",
        "price": 1500,
        "is_sale": false
      }
    ],
    "for カテア": [
      {
        "date": "2026-01-18",
        "price": 1500,
        "is_sale": false
      },
      {
        "date": "2026-01-19",
        "price": 1500,
        "is_sale": false
      },
      {
        "date": "2026-01-20",
        "price": 1500,
        "is_sale": false
      }
    ],
    "for セレスティア": [
      {
        "date": "2026-01-18",
        "price": 1500,
        "is_sale": false
      },
      {
        "date": "2026-01-19",
        "price": 1500,
        "is_sale": false
      },
      {
        "date": "2026-01-20",
        "price": 1500,
        "is_sale": false
      }
    ],
    "for 萌": [
      {
        "date": "2026-01-18",
        "price": 1500,
        "is_sale": false
      },
      {
        "date": "2026-01-19",
        "price": 1500,
        "is_sale": false
      },
      {
        "date": "2026-01-20",
        "price": 1500,
        "is_sale": false
      }
    ],
    "for 桔梗": [
      {
        "date": "2026-01-18",
        "price": 1500,
        "is_sale": false
      },
      {
        "date": "2026-01-19",
        "price": 1500,
        "is_sale": false
      },
      {
        "date": "2026-01-20",
        "price": 1500,
        "is_sale": false
      }
    ]
  }
}