{
  "id": "7801249",
  "name": "❄️Snow Charm☃️| ❄️雪のチャーム☃️",
  "variations": {
    "Full Pack❄️": [
      {
        "date": "2026-01-16",
        "price": 900,
        "is_sale": false
      },
      {
        "date": "2026-01-18",
        "price": 900,
        "is_sale": false
      }
    ],
    "Lumina [ルミナ]": [
      {
        "date": "2026-01-16",
        "price": 600,
        "is_sale": false
      },
      {
        "date": "2026-01-18",
        "price": 600,
        "is_sale": false
      }
    ],
    "Milltina [ミルティナ]": [
      {
        "date": "2026-01-16",
        "price": 600,
        "is_sale": false
      },
      {
        "date": "2026-01-18",
        "price": 600,
        "is_sale": false
      }
    ],
    "Ichigo [イチゴ]": [
      {
        "date": "2026-01-16",
        "price": 600,
        "is_sale": false
      },
      {
        "date": "2026-01-18",
        "price": 600,
        "is_sale": false
      }
    ],
    "Shinano [しなの]": [
      {
        "date": "2026-01-16",
        "price": 600,
        "is_sale": false
      },
      {
        "date": "2026-01-18",
        "price": 600,
        "is_sale": false
      }
    ],
    "Kisha [キシャ]": [
      {
        "date": "2026-01-16",
        "price": 600,
        "is_sale": false
      },
      {
        "date": "2026-01-18",
        "price": 600,
        "is_sale": false
      }
    ],
    "Airi [愛莉]": [
      {
        "date": "2026-01-16",
        "price": 600,
        "is_sale": false
      },
      {
        "date": "2026-01-18",
        "price": 600,
        "is_sale": false
      }
    ],
    "Sio [しお]": [
      {
        "date": "2026-01-16",
        "price": 600,
        "is_sale": false
      },
      {
        "date": "2026-01-18",
        "price": 600,
        "is_sale": false
      }
    ]
  }
}