{
  "id": "6477623",
  "name": "【VRChat想定MA対応】武器召喚魔法(和風)「Sorcery Weapon2」【3Dモデル、パーティクル】",
  "variations": {
    "default": [
      {
        "date": "2026-01-17",
        "price": 500,
        "is_sale": false
      },
      {
        "date": "2026-01-19",
        "price": 500,
        "is_sale": false
      },
      {
        "date": "2026-01-20",
        "price": 500,
        "is_sale": false
      },
      {
        "date": "2026-01-22",
        "price": 500,
        "is_sale": false
      },
      {
        "date": "2026-01-23",
        "price": 500,
        "is_sale": false
      },
      {
        "date": "2026-01-24",
        "price": 500,
        "is_sale": false
      },
      {
        "date": "2026-01-25",
        "price": 500,
        "is_sale": false
      }
    ]
  }
}