{
  "id": "4618036",
  "name": "フラワーディアンドル（９アバター対応）",
  "variations": {
    "フルセット": [
      {
        "date": "2026-01-18",
        "price": 3400,
        "is_sale": false
      }
    ],
    "桔梗": [
      {
        "date": "2026-01-18",
        "price": 1700,
        "is_sale": false
      }
    ],
    "セレスティア": [
      {
        "date": "2026-01-18",
        "price": 1700,
        "is_sale": false
      }
    ],
    "透羽": [
      {
        "date": "2026-01-18",
        "price": 1700,
        "is_sale": false
      }
    ],
    "ルキフェル（まるぼでぃ）": [
      {
        "date": "2026-01-18",
        "price": 1700,
        "is_sale": false
      }
    ],
    "カリン": [
      {
        "date": "2026-01-18",
        "price": 1700,
        "is_sale": false
      }
    ],
    "リミリア": [
      {
        "date": "2026-01-18",
        "price": 1700,
        "is_sale": false
      }
    ],
    "INABA": [
      {
        "date": "2026-01-18",
        "price": 1700,
        "is_sale": false
      }
    ],
    "めいゆん": [
      {
        "date": "2026-01-18",
        "price": 1700,
        "is_sale": false
      }
    ],
    "萌": [
      {
        "date": "2026-01-18",
        "price": 1700,
        "is_sale": false
      }
    ]
  }
}