{
  "id": "7505711",
  "name": "【VRCHAT】⛩️夜宴⛩️【＋Head/MOCBody_M/Marubody/Lapwing/IOLI&VAZILE/クラエナ対応衣装】",
  "variations": {
    "＋Head": [
      {
        "date": "2026-01-16",
        "price": 1000,
        "is_sale": false
      }
    ],
    "MOCBody_M": [
      {
        "date": "2026-01-16",
        "price": 1000,
        "is_sale": false
      }
    ],
    "Marubody": [
      {
        "date": "2026-01-16",
        "price": 1000,
        "is_sale": false
      }
    ],
    "IOLI&VAZILE": [
      {
        "date": "2026-01-16",
        "price": 1000,
        "is_sale": false
      }
    ],
    "Lapwing": [
      {
        "date": "2026-01-16",
        "price": 1000,
        "is_sale": false
      }
    ],
    "クラエナ": [
      {
        "date": "2026-01-16",
        "price": 1000,
        "is_sale": false
      }
    ],
    "フルパック": [
      {
        "date": "2026-01-16",
        "price": 2000,
        "is_sale": false
      }
    ]
  }
}