{
  "id": "8109328",
  "name": "вџЎ ЭЃв‚Љ .гЂ–FreeгЂ—е„љгЃ’ Face pack / BlendShapeпј‹face anim гЂ–MilltinaгЂ—",
  "variations": {
    "default": [
      {
        "date": "2026-03-22",
        "price": 0,
        "is_sale": false
      },
      {
        "date": "2026-03-24",
        "price": 0,
        "is_sale": false
      },
      {
        "date": "2026-03-25",
        "price": 0,
        "is_sale": false
      },
      {
        "date": "2026-03-27",
        "price": 0,
        "is_sale": false
      },
      {
        "date": "2026-03-28",
        "price": 0,
        "is_sale": false
      }
    ]
  }
}