{
  "id": "8090446",
  "name": "mao・rurune仮面",
  "variations": {
    "mao仮面": [
      {
        "date": "2026-03-18",
        "price": 300,
        "is_sale": false
      },
      {
        "date": "2026-03-20",
        "price": 300,
        "is_sale": false
      }
    ],
    "rurune仮面": [
      {
        "date": "2026-03-18",
        "price": 300,
        "is_sale": false
      },
      {
        "date": "2026-03-20",
        "price": 300,
        "is_sale": false
      }
    ],
    "mao,rurune仮面セット": [
      {
        "date": "2026-03-18",
        "price": 500,
        "is_sale": false
      },
      {
        "date": "2026-03-20",
        "price": 500,
        "is_sale": false
      }
    ]
  }
}