{
  "id": "2461808",
  "name": "VRChat想定オリジナル3Dモデル お菓子の飛び出すジャックランタン",
  "variations": {
    "無料版": [
      {
        "date": "2026-01-18",
        "price": 0,
        "is_sale": false
      },
      {
        "date": "2026-01-20",
        "price": 0,
        "is_sale": false
      },
      {
        "date": "2026-01-21",
        "price": 0,
        "is_sale": false
      },
      {
        "date": "2026-01-22",
        "price": 0,
        "is_sale": false
      },
      {
        "date": "2026-01-23",
        "price": 0,
        "is_sale": false
      },
      {
        "date": "2026-01-25",
        "price": 0,
        "is_sale": false
      },
      {
        "date": "2026-01-26",
        "price": 0,
        "is_sale": false
      },
      {
        "date": "2026-01-27",
        "price": 0,
        "is_sale": false
      },
      {
        "date": "2026-01-28",
        "price": 0,
        "is_sale": false
      }
    ],
    "作者にお菓子をあげる": [
      {
        "date": "2026-01-18",
        "price": 200,
        "is_sale": false
      },
      {
        "date": "2026-01-20",
        "price": 200,
        "is_sale": false
      },
      {
        "date": "2026-01-21",
        "price": 200,
        "is_sale": false
      },
      {
        "date": "2026-01-22",
        "price": 200,
        "is_sale": false
      },
      {
        "date": "2026-01-23",
        "price": 200,
        "is_sale": false
      },
      {
        "date": "2026-01-25",
        "price": 200,
        "is_sale": false
      },
      {
        "date": "2026-01-26",
        "price": 200,
        "is_sale": false
      },
      {
        "date": "2026-01-27",
        "price": 200,
        "is_sale": false
      },
      {
        "date": "2026-01-28",
        "price": 200,
        "is_sale": false
      }
    ]
  }
}